superposition_provider/__init__.py
superposition_provider/cac_config.py
superposition_provider/configuration_client.py
superposition_provider/exp_config.py
superposition_provider/provider.py
superposition_provider/types.py
superposition_bindings/__init__.py
superposition_bindings/libsuperposition_core-aarch64-apple-darwin.dylib
superposition_bindings/libsuperposition_core-x86_64-apple-darwin.dylib
superposition_bindings/libsuperposition_core-x86_64-pc-windows-msvc.dll
superposition_bindings/libsuperposition_core-x86_64-unknown-linux-gnu.so
superposition_bindings/superposition_client.py
superposition_bindings/superposition_types.py
superposition_sdk/__init__.py
superposition_sdk/auth.py
superposition_sdk/auth_helpers.py
superposition_sdk/client.py
superposition_sdk/config.py
superposition_sdk/deserialize.py
superposition_sdk/models.py
superposition_sdk/serialize.py
superposition_sdk/_private/__init__.py
superposition_sdk/_private/schemas.py
superposition_provider-0.97.4.dist-info/METADATA
superposition_provider-0.97.4.dist-info/WHEEL
superposition_provider-0.97.4.dist-info/RECORD
