Metadata-Version: 2.4
Name: superposition_provider
Version: 0.97.4
Summary: superposition_provider
License: Apache-2.0
Keywords: openfeature,superposition_provider
Requires-Python: >=3.12
Requires-Dist: smithy-core==0.0.1
Requires-Dist: smithy-http[aiohttp]==0.0.1
Requires-Dist: smithy-json==0.0.1
